torchcnnbuilder/__init__.py
torchcnnbuilder/_formulas.py
torchcnnbuilder/_utils.py
torchcnnbuilder/_validation.py
torchcnnbuilder/_version.py
torchcnnbuilder/builder.py
torchcnnbuilder/constants.py
torchcnnbuilder/latent.py
torchcnnbuilder/models.py
torchcnnbuilder/preprocess/__init__.py
torchcnnbuilder/preprocess/_dynamic_window.py
torchcnnbuilder-0.1.5.dist-info/LICENSE
torchcnnbuilder-0.1.5.dist-info/METADATA
torchcnnbuilder-0.1.5.dist-info/WHEEL
torchcnnbuilder-0.1.5.dist-info/top_level.txt
torchcnnbuilder-0.1.5.dist-info/RECORD
