Metadata-Version: 2.1
Name: torchcnnbuilder
Version: 0.1.5
Summary: Framework for the automatic creation of CNN architectures
Home-page: https://github.com/ChrisLisbon/TorchCNNBuilder
Author: Andrew Kuznetsov, Julia Borisova, Nikolay O. Nikitin
Author-email: just.andrew.kd@gmail.com
Keywords: python torch cnn
Classifier: Development Status :: 3 - Alpha
Classifier: Intended Audience :: Developers
Classifier: Intended Audience :: Science/Research
Classifier: Programming Language :: Python :: 3.9
Classifier: Programming Language :: Python :: 3.10
Classifier: Programming Language :: Python :: 3.11
Classifier: License :: OSI Approved :: BSD License
Classifier: Operating System :: OS Independent
Requires-Python: >=3.9
License-File: LICENSE
Requires-Dist: torch >=2.0.0
